{"day": "tuesday", "shows": [{"name": "Garbage Theater", "desc": "The Content Manager\u2019s legacy\u2026", "hosts": "Scott Rabies", "poster": "https://raw.githubusercontent.com/WJTB-Radio/ShowData/master/images/8c386ea7394dce7b9fd9427d2fc90414.jpg", "start_time": 36000, "end_time": 39600, "is_running": 1}, {"name": "Drop Table", "desc": "honestly we don't even know at this point . one time niko had a car crash live on air, the only constant is internet music", "hosts": "curro & niko", "poster": "https://raw.githubusercontent.com/WJTB-Radio/ShowData/master/images/8c386ea7394dce7b9fd9427d2fc90414.jpg", "start_time": 41400, "end_time": 46800, "is_running": 1}]}